kivy_uix/__init__.py
kivy_uix/version.py
kivy_uix-1.0.0.dist-info/LICENSE
kivy_uix-1.0.0.dist-info/METADATA
kivy_uix-1.0.0.dist-info/WHEEL
kivy_uix-1.0.0.dist-info/top_level.txt
kivy_uix-1.0.0.dist-info/zip-safe
kivy_uix-1.0.0.dist-info/RECORD
